adapter_engine/__init__.py
adapter_engine/api/__init__.py
adapter_engine/lib/__init__.py
adapter_engine/lib/core/__init__.py
adapter_engine/lib/core/common.py
adapter_engine/lib/core/data.py
adapter_engine/lib/core/datatype.py
adapter_engine/lib/core/decorators.py
adapter_engine/lib/core/enums.py
adapter_engine/lib/core/exception.py
adapter_engine/lib/core/interpreter_option.py
adapter_engine/lib/core/log.py
adapter_engine/lib/core/option.py
adapter_engine/lib/core/poc.py
adapter_engine/lib/core/register.py
adapter_engine/lib/core/settings.py
adapter_engine/lib/nuclei/__init__.py
adapter_engine/lib/nuclei/extractors.py
adapter_engine/lib/nuclei/filter.py
adapter_engine/lib/nuclei/interfaces.py
adapter_engine/lib/nuclei/matchers.py
adapter_engine/lib/nuclei/protocols.py
adapter_engine/lib/nuclei/template.py
adapter_engine/lib/request/__init__.py
adapter_engine/lib/request/patch/__init__.py
adapter_engine/lib/request/patch/add_httpraw.py
adapter_engine/lib/request/patch/remove_ssl_verify.py
adapter_engine/lib/request/patch/remove_warnings.py
adapter_engine/lib/utils/__init__.py
adapter_engine/thirdparty/__init__.py
adapter_engine/thirdparty/requests_raw/__init__.py
adapter_engine/thirdparty/requests_raw/__version__.py
adapter_engine/thirdparty/requests_raw/adapters.py
adapter_engine/thirdparty/requests_raw/api.py
adapter_engine/thirdparty/requests_raw/connection.py
adapter_engine/thirdparty/requests_raw/connectionpool.py
adapter_engine/thirdparty/requests_raw/sessions.py
adapter_engine-0.0.2.dist-info/LICENSE
adapter_engine-0.0.2.dist-info/METADATA
adapter_engine-0.0.2.dist-info/WHEEL
adapter_engine-0.0.2.dist-info/top_level.txt
adapter_engine-0.0.2.dist-info/RECORD
